hapanapi/__init__.py
hapanapi/constants.py
hapanapi/driver_tools.py
hapanapi/parsers.py
hapanapi-0.37.dist-info/LICENSE
hapanapi-0.37.dist-info/METADATA
hapanapi-0.37.dist-info/WHEEL
hapanapi-0.37.dist-info/top_level.txt
hapanapi-0.37.dist-info/RECORD
