Metadata-Version: 2.1
Name: hapanapi
Version: 0.37
Summary: Simple Python Wrapper for scraping and accessing Hapana Data
Home-page: https://github.com/REVL-Training/HapanaAPI
Author: Liew Cher Don
Author-email: liewcherdon@gmail.com
License: UNKNOWN
Platform: UNKNOWN
Classifier: Programming Language :: Python :: 3.8
Classifier: License :: OSI Approved :: MIT License
Classifier: Operating System :: OS Independent
License-File: LICENSE
